service_toolkit/panic.py
service_toolkit-0.1.0.dist-info/METADATA
service_toolkit-0.1.0.dist-info/WHEEL
service_toolkit-0.1.0.dist-info/RECORD
